pyebus/__init__.py
pyebus/__main__.py
pyebus/circuitinfo.py
pyebus/circuitinfodecoder.py
pyebus/circuitmap.py
pyebus/cli/__init__.py
pyebus/cli/cmd.py
pyebus/cli/common.py
pyebus/cli/dummyserver.py
pyebus/cli/info.py
pyebus/cli/listen.py
pyebus/cli/ls.py
pyebus/cli/observe.py
pyebus/cli/read.py
pyebus/cli/state.py
pyebus/cli/write.py
pyebus/connection.py
pyebus/const.py
pyebus/dummy.py
pyebus/dummyconnection.py
pyebus/dummydata.py
pyebus/dummyserver.py
pyebus/ebus.py
pyebus/exceptions.py
pyebus/icon.py
pyebus/msg.py
pyebus/msgdecoder.py
pyebus/msgdef.py
pyebus/msgdefdecoder.py
pyebus/msgdefs.py
pyebus/na.py
pyebus/prioritizer.py
pyebus/typedecoder.py
pyebus/types.py
pyebus/util.py
pyebus/virtfielddef.py
pyebus-1.4.0.dist-info/entry_points.txt
pyebus-1.4.0.dist-info/WHEEL
pyebus-1.4.0.dist-info/METADATA
pyebus-1.4.0.dist-info/RECORD
