Metadata-Version: 2.1
Name: pyebus
Version: 1.4.0
Summary: Pythonic Interface to EBUS Daemon (ebusd)
Home-page: https://github.com/c0fec0de/pyebus
License: MIT
Keywords: EBUSD,EBUS,Dungs,FH Ostfalia,TEM,Lamberti,CEB,Landis-Staefa,FERRO,MONDIAL,Wikon,Wolf,RAWE,Satronic,ENCON,Kromschröder,Eberle,EBV,Grässlin,ebm-papst,SIG,Theben,Thermowatt,Vaillant,Toby,Weishaupt,ebusd.eu,Heating
Author: c0fec0de
Author-email: c0fec0de@gmail.com
Requires-Python: >=3.7,<4
Classifier: Development Status :: 5 - Production/Stable
Classifier: License :: OSI Approved :: MIT License
Classifier: Programming Language :: Python :: 3
Classifier: Programming Language :: Python :: 3.10
Classifier: Programming Language :: Python :: 3.7
Classifier: Programming Language :: Python :: 3.8
Classifier: Programming Language :: Python :: 3.9
Classifier: Topic :: Software Development :: Libraries :: Python Modules
Requires-Dist: anytree (>=2.8.0,<3.0.0)
Project-URL: Repository, https://github.com/c0fec0de/pyebus
